textrank/__init__.py
textrank/access.py
textrank/admin.py
textrank/analyzer.py
textrank/apps.py
textrank/conf.py
textrank/decorators.py
textrank/forms.py
textrank/models.py
textrank/urls.py
textrank/validators.py
textrank/locale/ru/LC_MESSAGES/django.po
textrank/migrations/0001_initial.py
textrank/migrations/0002_sample.py
textrank/migrations/0003_group_description.py
textrank/migrations/0004_alter_group_name.py
textrank/migrations/0005_auto_20210924_0805.py
textrank/migrations/__init__.py
textrank/templates/textrank/_is_active_button.html
textrank/templates/textrank/_navbar.html
textrank/templates/textrank/_search_form.html
textrank/templates/textrank/_table_pagination.html
textrank/templates/textrank/base.html
textrank/templates/textrank/groups.html
textrank/templates/textrank/index.html
textrank/templates/textrank/keywords.html
textrank/templates/textrank/rank.html
textrank/templates/textrank/samples.html
textrank/templates/textrank/topics.html
textrank/views/__init__.py
textrank/views/base.py
textrank/views/pages.py
django_textrank-1.0.1.dist-info/AUTHORS
django_textrank-1.0.1.dist-info/LICENSE
django_textrank-1.0.1.dist-info/METADATA
django_textrank-1.0.1.dist-info/WHEEL
django_textrank-1.0.1.dist-info/top_level.txt
django_textrank-1.0.1.dist-info/RECORD
