Metadata-Version: 2.1
Name: django-textrank
Version: 1.0.1
Summary: This is a Django reusable application for ranging a text by keywords.
Home-page: https://gitlab.com/djbaldey/django-textrank/
Author: Grigoriy Kramarenko
Author-email: root@rosix.ru
License: BSD License
Platform: any
Classifier: Development Status :: 5 - Production/Stable
Classifier: Environment :: Web Environment
Classifier: Framework :: Django
Classifier: Framework :: Django :: 2.2
Classifier: Framework :: Django :: 3.2
Classifier: Intended Audience :: Developers
Classifier: License :: OSI Approved :: BSD License
Classifier: Natural Language :: Russian
Classifier: Operating System :: OS Independent
Classifier: Programming Language :: Python
Classifier: Programming Language :: Python :: 3.7
Classifier: Programming Language :: Python :: 3.8
Classifier: Programming Language :: Python :: 3.9
Classifier: Topic :: Internet :: WWW/HTTP
Classifier: Topic :: Internet :: WWW/HTTP :: Dynamic Content
Requires-Dist: django (>=2.2)
Requires-Dist: djangokit (>=0.1)
Requires-Dist: pymorphy2 (>=0.8)
